setup.py
sara_distributions/Binomialdistribution.py
sara_distributions/Gaussiandistribution.py
sara_distributions/Generaldistribution.py
sara_distributions/__init__.py
sara_distributions.egg-info/PKG-INFO
sara_distributions.egg-info/SOURCES.txt
sara_distributions.egg-info/dependency_links.txt
sara_distributions.egg-info/not-zip-safe
sara_distributions.egg-info/top_level.txt