Metadata-Version: 1.0
Name: sara-distributions
Version: 0.1
Summary: Gaussian distributions
Home-page: UNKNOWN
Author: Sara Jalali
Author-email: sr.jalali@gmail.com
License: UNKNOWN
Platform: UNKNOWN
